marvell_11abbe00/__init__.py
marvell_11abbe00/builder.py
marvell_11abbe00/endpoints.py
marvell_11abbe00/replay.py
marvell_11abbe00/response.py
marvell_11abbe00/switch.py
marvell_11abbe00-0.0.8.dist-info/METADATA
marvell_11abbe00-0.0.8.dist-info/WHEEL
marvell_11abbe00-0.0.8.dist-info/entry_points.txt
marvell_11abbe00-0.0.8.dist-info/licenses/LICENSE
marvell_11abbe00-0.0.8.dist-info/RECORD
