Metadata-Version: 2.3
Name: marvell_11abbe00
Version: 0.0.8
Summary: A library for manipulating configuration in cisco/marvell switches integrated into ENCS54xx platform
Project-URL: Homepage, https://github.com/yeyus/marvell-11abbe00
Project-URL: Issues, https://github.com/yeyus/marvell-11abbe00/issues
Author-email: yeyus <elyeyus@gmail.com>
License-File: LICENSE
Classifier: License :: OSI Approved :: MIT License
Classifier: Operating System :: OS Independent
Classifier: Programming Language :: Python :: 3
Requires-Python: >=3.8
Requires-Dist: haralyzer==2.4.0
Requires-Dist: requests==2.31.0
